atus/icon.ico
atus/main.py
atus/version.txt
atus/images/icons/add_white-24px.svg
atus/images/icons/attach_file_white_24dp.svg
atus/images/icons/calculator-18px.svg
atus/images/icons/chart-18px.svg
atus/images/icons/check_white_24dp.svg
atus/images/icons/close-24px.svg
atus/images/icons/close_black_24dp.svg
atus/images/icons/content_copy_black_24dp.svg
atus/images/icons/delete-18px.svg
atus/images/icons/expand_more_white_18dp.svg
atus/images/icons/file-18px.svg
atus/images/icons/functions_white_24dp.svg
atus/images/icons/get_app_black_24dp.svg
atus/images/icons/github-36px.svg
atus/images/icons/histogram-18px.svg
atus/images/icons/home-36px.svg
atus/images/icons/info-18px.svg
atus/images/icons/ios_share_white_24dp.svg
atus/images/icons/lock-open-variant-outline.svg
atus/images/icons/lock-outline.svg
atus/images/icons/multichart-18px.svg
atus/images/icons/settings_black_24dp.svg
atus/images/icons/settings_white_24dp.svg
atus/images/main_icon/ATUS_Logo_Cinza_2_Tagline.png
atus/images/main_icon/ATUS_icon.svg
atus/images/main_icon/ATUS_logo_preto.svg
atus/images/main_icon/Atus_icon.png
atus/images/svg_images/calculator_icon.svg
atus/images/svg_images/close_icon.svg
atus/images/svg_images/close_white_24dp.svg
atus/images/svg_images/compare_arrows_white_24dp.svg
atus/images/svg_images/create_white_24dp.svg
atus/images/svg_images/examples_icon.svg
atus/images/svg_images/expand_less_white_24dp.svg
atus/images/svg_images/expand_more_white_24dp.svg
atus/images/svg_images/histogram_icon.svg
atus/images/svg_images/home_icon.svg
atus/images/svg_images/icon_app_top.svg
atus/images/svg_images/info_icon.svg
atus/images/svg_images/maximize_icon.svg
atus/images/svg_images/menu_icon.svg
atus/images/svg_images/menu_white_24dp.svg
atus/images/svg_images/minimize_icon.svg
atus/images/svg_images/minimize_white_24dp.svg
atus/images/svg_images/multiplot_icon.svg
atus/images/svg_images/open_icon.svg
atus/images/svg_images/plot_icon.svg
atus/images/svg_images/resize_icon.svg
atus-1.3.1.dist-info/licenses/LICENSE
atus-1.3.1.dist-info/METADATA
atus-1.3.1.dist-info/WHEEL
atus-1.3.1.dist-info/entry_points.txt
atus-1.3.1.dist-info/top_level.txt
atus-1.3.1.dist-info/RECORD
