Metadata-Version: 2.4
Name: atus
Version: 1.3.1
Home-page: https://github.com/HighEloDevs/Analysis-Tool-for-Undergrad-Students
Author: High Elo Devs
Author-email: atusdevs@gmail.com
Project-URL: Bug Tracker, https://github.com/HighEloDevs/Analysis-Tool-for-Undergrad-Students/issues
Classifier: Programming Language :: Python :: 3
Classifier: License :: OSI Approved :: MIT License
Classifier: Operating System :: OS Independent
Requires-Python: >3.8, <3.12
License-File: LICENSE
Requires-Dist: setuptools>=42
Requires-Dist: lmfit==1.1.0
Requires-Dist: matplotlib==3.6.2
Requires-Dist: IPython==8.10.0
Requires-Dist: numpy==1.23.5
Requires-Dist: pandas==1.5.2
Requires-Dist: PyQt5==5.15.6
Requires-Dist: requests==2.28.1
Requires-Dist: scipy==1.9.3
Requires-Dist: pytexit==0.4.0
Dynamic: author
Dynamic: author-email
Dynamic: classifier
Dynamic: description
Dynamic: description-content-type
Dynamic: home-page
Dynamic: license-file
Dynamic: project-url
Dynamic: requires-dist
Dynamic: requires-python
